aws_access_util/__init__.py
aws_access_util/get_aws_access.py
aws_access_util/common/__init__.py
aws_access_util/common/aws_utilities.py
aws_access_util/common/duo_utilities.py
aws_access_util/constants/__init__.py
aws_access_util/constants/constants.py
aws_access_util/template/__init__.py
aws_access-1.1.2.dist-info/METADATA
aws_access-1.1.2.dist-info/WHEEL
aws_access-1.1.2.dist-info/top_level.txt
aws_access-1.1.2.dist-info/RECORD
