Metadata-Version: 2.1
Name: aws-access
Version: 1.1.2
Summary: This package is used to get temporary token for aws access
Home-page: https://bitbucket-eng-sjc1.cisco.com/bitbucket/scm/con/hyperloop.git
Author: Mounika Gorintla
Author-email: mgorintl@cisco.com
License: UNKNOWN
Platform: UNKNOWN
Classifier: Programming Language :: Python :: 3
Classifier: License :: OSI Approved :: Apache Software License
Classifier: Operating System :: OS Independent
Requires-Python: >=3.7
Requires-Dist: requests
Requires-Dist: beautifulsoup4 (==4.8.2)
Requires-Dist: jinja2
Requires-Dist: configparser
Requires-Dist: boto3
Requires-Dist: botocore
Requires-Dist: awscli
Requires-Dist: defusedxml
